cproxchecker/__init__.py
cproxchecker/crpox.py
cproxchecker-0.2.0.dist-info/METADATA
cproxchecker-0.2.0.dist-info/WHEEL
cproxchecker-0.2.0.dist-info/top_level.txt
cproxchecker-0.2.0.dist-info/RECORD
